KeaiDePython/README.md
KeaiDePython/__init__.py
KeaiDePython/__main__.py
KeaiDePython/file.epub
KeaiDePython/index.html
KeaiDePython/css/__init__.py
KeaiDePython/css/annotations.css
KeaiDePython/css/main.css
KeaiDePython/css/normalize.css
KeaiDePython/css/popup.css
KeaiDePython/font/__init__.py
KeaiDePython/font/fontello.eot
KeaiDePython/font/fontello.svg
KeaiDePython/font/fontello.ttf
KeaiDePython/font/fontello.woff
KeaiDePython/img/__init__.py
KeaiDePython/img/annotator-glyph-sprite.png
KeaiDePython/img/annotator-icon-sprite.png
KeaiDePython/img/apple-touch-icon.png
KeaiDePython/img/cancelfullscreen.png
KeaiDePython/img/close.png
KeaiDePython/img/fullscreen.png
KeaiDePython/img/loader.gif
KeaiDePython/img/menu-icon.png
KeaiDePython/img/save.png
KeaiDePython/img/saved.png
KeaiDePython/img/settings-s.png
KeaiDePython/img/settings.png
KeaiDePython/img/star.png
KeaiDePython/js/__init__.py
KeaiDePython/js/epub.js
KeaiDePython/js/epub.min.js
KeaiDePython/js/epub.min.map
KeaiDePython/js/hooks.min.js
KeaiDePython/js/hooks.min.map
KeaiDePython/js/reader.js
KeaiDePython/js/reader.js.map
KeaiDePython/js/reader.min.js
KeaiDePython/js/reader.min.map
KeaiDePython/js/hooks/__init__.py
KeaiDePython/js/hooks/extensions/__init__.py
KeaiDePython/js/hooks/extensions/highlight.js
KeaiDePython/js/libs/__init__.py
KeaiDePython/js/libs/jquery.min.js
KeaiDePython/js/libs/localforage.min.js
KeaiDePython/js/libs/screenfull.js
KeaiDePython/js/libs/screenfull.min.js
KeaiDePython/js/libs/zip.min.js
KeaiDePython/js/plugins/__init__.py
KeaiDePython/js/plugins/hypothesis.js
KeaiDePython/js/plugins/search.js
keai_de_python-2024.3.1.0.dist-info/METADATA
keai_de_python-2024.3.1.0.dist-info/WHEEL
keai_de_python-2024.3.1.0.dist-info/entry_points.txt
keai_de_python-2024.3.1.0.dist-info/top_level.txt
keai_de_python-2024.3.1.0.dist-info/RECORD
